publichost/__init__.py
publichost/exceptions.py
publichost/tunnel.py
publichost/utils.py
publichost-0.1.6.dist-info/METADATA
publichost-0.1.6.dist-info/WHEEL
publichost-0.1.6.dist-info/licenses/LICENSE
publichost-0.1.6.dist-info/RECORD
