Metadata-Version: 2.4
Name: publichost
Version: 0.1.6
Summary: Make localhost public in one line
Project-URL: Homepage, https://publichost.dev
Project-URL: Documentation, https://pypi.org/project/publichost
Author-email: Spencer Kinney <email@spencerkinney.dev>
License: # LICENSE
License-File: LICENSE
Keywords: development,localhost,networking,tunnel
Classifier: License :: OSI Approved :: MIT License
Classifier: Programming Language :: Python
Classifier: Programming Language :: Python :: 3
Classifier: Programming Language :: Python :: 3.8
Classifier: Programming Language :: Python :: 3.9
Classifier: Programming Language :: Python :: 3.10
Classifier: Programming Language :: Python :: 3.11
Classifier: Programming Language :: Python :: 3.12
Classifier: Programming Language :: Python :: 3.13
Requires-Python: >=3.8
Requires-Dist: aiohttp>=3.8.0
Requires-Dist: websockets>=10.0
